setup.py
odoo/addons/widget_list_message/CHANGELOG.md
odoo/addons/widget_list_message/README.rst
odoo/addons/widget_list_message/__init__.py
odoo/addons/widget_list_message/__manifest__.py
odoo/addons/widget_list_message/i18n/ca_ES.po
odoo/addons/widget_list_message/i18n/es.po
odoo/addons/widget_list_message/static/description/icon.png
odoo/addons/widget_list_message/static/src/css/styles.css
odoo/addons/widget_list_message/static/src/js/list_message_group.js
odoo/addons/widget_list_message/static/src/js/list_message_tooltip.js
odoo/addons/widget_list_message/static/src/js/list_renderer.js
odoo/addons/widget_list_message/static/src/js/relative_date_formatter.js
odoo/addons/widget_list_message/static/src/xml/templates.xml
odoo_addon_widget_list_message.egg-info/PKG-INFO
odoo_addon_widget_list_message.egg-info/SOURCES.txt
odoo_addon_widget_list_message.egg-info/dependency_links.txt
odoo_addon_widget_list_message.egg-info/not-zip-safe
odoo_addon_widget_list_message.egg-info/requires.txt
odoo_addon_widget_list_message.egg-info/top_level.txt