Metadata-Version: 2.1
Name: odoo-addon-widget-list-message
Version: 16.0.1.0.5
Summary: SomItCoop ODOO widget to set limit columns on list view.
Home-page: https://gitlab.com/somitcoop/erp-research/odoo-helpdesk
Author: Som It Cooperatiu SCCL, Som Connexió SCCL, Odoo Community Association (OCA)
Author-email: support@odoo-community.org
License: AGPL-3
Classifier: Programming Language :: Python
Classifier: Framework :: Odoo
Classifier: Framework :: Odoo :: 16.0
Classifier: License :: OSI Approved :: GNU Affero General Public License v3
Requires-Python: >=3.10
